video_transcriber_gui/__init__.py
video_transcriber_gui/app.py
video_transcriber_gui/config.py
video_transcriber_gui/transcription.py
video_transcriber_gui-0.1.1.dist-info/licenses/LICENSE
video_transcriber_gui-0.1.1.dist-info/METADATA
video_transcriber_gui-0.1.1.dist-info/WHEEL
video_transcriber_gui-0.1.1.dist-info/entry_points.txt
video_transcriber_gui-0.1.1.dist-info/top_level.txt
video_transcriber_gui-0.1.1.dist-info/RECORD
