Metadata-Version: 2.4
Name: video-transcriber-gui
Version: 0.1.1
Summary: A command line GUI for video-transcriber based on textual
Author-email: Romilly Cocking <romilly.cocking@gmail.com>
License: MIT
Project-URL: Homepage, https://github.com/romilly/video-transcriber-gui
Project-URL: Repository, https://github.com/romilly/video-transcriber-gui.git
Project-URL: Issues, https://github.com/romilly/video-transcriber-gui/issues
Classifier: Development Status :: 3 - Alpha
Classifier: Intended Audience :: Developers
Classifier: License :: OSI Approved :: MIT License
Classifier: Programming Language :: Python :: 3
Classifier: Programming Language :: Python :: 3.10
Classifier: Programming Language :: Python :: 3.11
Classifier: Programming Language :: Python :: 3.12
Requires-Python: >=3.10
License-File: LICENSE
Requires-Dist: textual>=0.89.0
Requires-Dist: textual-fspicker>=0.6.0
Requires-Dist: video-transcriber
Provides-Extra: test
Requires-Dist: pytest>=7.0.0; extra == "test"
Requires-Dist: pytest-cov; extra == "test"
Requires-Dist: pytest-asyncio; extra == "test"
Dynamic: license-file
